README.rst
setup.py
denormalize/__init__.py
denormalize/context.py
denormalize/middleware.py
denormalize/models.py
denormalize/signals.py
denormalize/utils.py
denormalize/backend/__init__.py
denormalize/backend/base.py
denormalize/backend/cache.py
denormalize/backend/locmem.py
denormalize/backend/mongodb.py
denormalize/integration/__init__.py
denormalize/integration/feincms_collection.py
denormalize/management/__init__.py
denormalize/management/commands/__init__.py
denormalize/management/commands/denormalize_sync.py
denormalize/tests/__init__.py
denormalize/tests/common.py
denormalize/tests/models.py
denormalize/tests/test_backends.py
denormalize/tests/test_collections.py
denormalize/tests/test_django.py
django_denormalize.egg-info/PKG-INFO
django_denormalize.egg-info/SOURCES.txt
django_denormalize.egg-info/dependency_links.txt
django_denormalize.egg-info/entry_points.txt
django_denormalize.egg-info/not-zip-safe
django_denormalize.egg-info/requires.txt
django_denormalize.egg-info/top_level.txt