Metadata-Version: 1.1
Name: django-denormalize
Version: 0.2.1
Summary: Converts Django ORM objects into data documents, and keeps them in sync
Home-page: https://bitbucket.org/wojas/django-denormalize/
Author: Konrad Wojas
Author-email: konrad@wojas.nl
License: LICENSE
Keywords: django orm cache mongodb nosql meteor
Platform: UNKNOWN
Classifier: Framework :: Django
Classifier: Intended Audience :: Developers
Classifier: Topic :: Database
Classifier: License :: OSI Approved :: MIT License
